settings/__init__.py
settings/admin.py
settings/apps.py
settings/business.py
settings/models.py
settings/tests.py
settings/urls.py
settings/views.py
settings/migrations/0001_initial.py
settings/migrations/__init__.py
settings/static/settings/settings.css
settings/templates/settings/change_list_template.html
settings/templates/settings/view_all_template.html
django_db_settings-1.2.1.dist-info/LICENSE
django_db_settings-1.2.1.dist-info/METADATA
django_db_settings-1.2.1.dist-info/WHEEL
django_db_settings-1.2.1.dist-info/top_level.txt
django_db_settings-1.2.1.dist-info/RECORD
