Metadata-Version: 2.1
Name: django-db-settings
Version: 1.2.1
Summary: A Django app to save app settings in DB as classes.
Home-page: https://github.com/oscargdi/django-db-settings
Author: Oscar Diaz
Author-email: oscargdi22@gmail.com
License: GNU General Public License v3.0
Platform: UNKNOWN
Classifier: Environment :: Web Environment
Classifier: Framework :: Django
Classifier: Framework :: Django :: 3.0
Classifier: Intended Audience :: Developers
Classifier: License :: OSI Approved :: BSD License
Classifier: Operating System :: OS Independent
Classifier: Programming Language :: Python
Classifier: Programming Language :: Python :: 3
Classifier: Programming Language :: Python :: 3 :: Only
Classifier: Programming Language :: Python :: 3.6
Classifier: Programming Language :: Python :: 3.7
Classifier: Programming Language :: Python :: 3.8
Classifier: Topic :: Internet :: WWW/HTTP
Classifier: Topic :: Internet :: WWW/HTTP :: Dynamic Content
Requires-Python: >3
Requires-Dist: django
Requires-Dist: cachetools
